fcast/__init__.py
fcast/event.py
fcast/event_type.py
fcast/media.py
fcast/message.py
fcast/opcode.py
fcast/session.py
fcast/utils.py
libfcast-3.5.1.dist-info/licenses/LICENSE
libfcast-3.5.1.dist-info/METADATA
libfcast-3.5.1.dist-info/WHEEL
libfcast-3.5.1.dist-info/top_level.txt
libfcast-3.5.1.dist-info/RECORD
