Metadata-Version: 2.4
Name: libfcast
Version: 3.5.1
Summary: FCast Python Lib
Author-email: Derivability <derivability@wraithgod.strangled.net>
License:                     GNU GENERAL PUBLIC LICENSE
Project-URL: Homepage, https://github.com/Derivability/FCast
Project-URL: Bug Reports, https://github.com/Derivability/FCast/issues
License-File: LICENSE
Dynamic: license-file
